thin_man-0.1.0.dev1.dist-info/top_level.txt
thin_man-0.1.0.dev1.dist-info/RECORD
thin_man-0.1.0.dev1.dist-info/WHEEL
thin_man-0.1.0.dev1.dist-info/metadata.json
thin_man-0.1.0.dev1.dist-info/entry_points.txt
thin_man-0.1.0.dev1.dist-info/DESCRIPTION.rst
thin_man-0.1.0.dev1.dist-info/METADATA
thinman/_compat.py
thinman/__main__.py
thinman/__init__.py
thin_man-0.1.0.dev1.data/data/EGG-INFO/LICENSE
thin_man-0.1.0.dev1.data/data/EGG-INFO/README.md
