Metadata-Version: 2.0
Name: thin-man
Version: 0.1.0.dev1
Summary: “Thin Man” backs up all metadata in your source tree of git repos.
Home-page: https://github.com/jhermann/thin-man
Author: Jürgen Hermann
Author-email: jh@web.de
License: Apache 2.0
Keywords: hosted.by.github,python,git,tool,backup,metadata
Platform: UNKNOWN
Classifier: Development Status :: 2 - Pre-Alpha
Classifier: Environment :: Console
Classifier: Intended Audience :: Developers
Classifier: Intended Audience :: System Administrators
Classifier: License :: OSI Approved :: Apache Software License
Classifier: Operating System :: OS Independent
Classifier: Programming Language :: Python :: 2
Classifier: Programming Language :: Python :: 2.7
Classifier: Programming Language :: Python :: 3
Classifier: Programming Language :: Python :: 3.4
Classifier: Topic :: Software Development :: Version Control
Classifier: Topic :: System :: Archiving :: Backup
Classifier: Topic :: System :: Archiving :: Mirroring
Classifier: Topic :: System :: Recovery Tools
Classifier: Topic :: Utilities
Requires-Dist: click (>=3.3,<4)
Requires-Dist: colorama
